fondy/__init__.py
fondy/currencies.py
fondy/fondy.py
fondy-0.3.5.dist-info/METADATA
fondy-0.3.5.dist-info/RECORD
fondy-0.3.5.dist-info/WHEEL
fondy-0.3.5.dist-info/top_level.txt
